[{"word": "fawn", "gender": "female"}, {"word": "nunnery", "gender": "female"}, {"word": "sunbonnet", "gender": "female"}, {"word": "yenta", "gender": "female"}, {"word": "knicker", "gender": "female"}, {"word": "mansion", "gender": "female"}, {"word": "grandparent", "gender": "female"}, {"word": "femicide", "gender": "female"}, {"word": "oocyte", "gender": "female"}, {"word": "bike", "gender": "female"}, {"word": "hausfrau", "gender": "female"}, {"word": "hormone", "gender": "female"}, {"word": "legislators", "gender": "female"}, {"word": "compassion", "gender": "female"}, {"word": "vase", "gender": "female"}, {"word": "forties", "gender": "female"}, {"word": "evert", "gender": "female"}, {"word": "chapel", "gender": "female"}, {"word": "school", "gender": "female"}, {"word": "moppet", "gender": "female"}, {"word": "satchel", "gender": "female"}, {"word": "charwoman", "gender": "female"}, {"word": "clothes", "gender": "female"}, {"word": "bicycle", "gender": "female"}, {"word": "quilt", "gender": "female"}, {"word": "ingenue", "gender": "female"}, {"word": "fraulein", "gender": "female"}, {"word": "kiva", "gender": "female"}, {"word": "street", "gender": "female"}, {"word": "washerman", "gender": "female"}, {"word": "crutch", "gender": "female"}, {"word": "coed", "gender": "female"}, {"word": "blouse", "gender": "female"}, {"word": "prostitutes", "gender": "female"}, {"word": "serape", "gender": "female"}, {"word": "fetish", "gender": "female"}, {"word": "misandry", "gender": "female"}, {"word": "groupie", "gender": "female"}, {"word": "motorist", "gender": "female"}, {"word": "screams", "gender": "female"}, {"word": "reporter", "gender": "female"}, {"word": "herd", "gender": "female"}, {"word": "anthropology", "gender": "female"}, {"word": "china", "gender": "female"}, {"word": "nanny", "gender": "female"}, {"word": "abbess", "gender": "female"}, {"word": "sorceress", "gender": "female"}, {"word": "blackpoll", "gender": "female"}, {"word": "kids", "gender": "female"}, {"word": "daughter", "gender": "female"}, {"word": "employees", "gender": "female"}, {"word": "cosmopolite", "gender": "female"}, {"word": "adolescents", "gender": "female"}, {"word": "fathered", "gender": "female"}, {"word": "bloomer", "gender": "female"}, {"word": "deaconess", "gender": "female"}, {"word": "servicemen", "gender": "female"}, {"word": "godmother", "gender": "female"}, {"word": "peahen", "gender": "female"}, {"word": "pantyhose", "gender": "female"}, {"word": "geisha", "gender": "female"}, {"word": "saleswomen", "gender": "female"}, {"word": "sweater", "gender": "female"}, {"word": "musk", "gender": "female"}, {"word": "females", "gender": "female"}, {"word": "huntress", "gender": "female"}, {"word": "trousers", "gender": "female"}, {"word": "phone", "gender": "female"}, {"word": "adult", "gender": "female"}, {"word": "boomer", "gender": "female"}, {"word": "ward", "gender": "female"}, {"word": "pouch", "gender": "female"}, {"word": "blindfold", "gender": "female"}, {"word": "flora", "gender": "female"}, {"word": "ma", "gender": "female"}, {"word": "paddlers", "gender": "female"}, {"word": "divorcee", "gender": "female"}, {"word": "laundress", "gender": "female"}, {"word": "genitalia", "gender": "female"}, {"word": "antifeminist", "gender": "female"}, {"word": "shool", "gender": "female"}, {"word": "gloria", "gender": "female"}, {"word": "household", "gender": "female"}, {"word": "leotards", "gender": "female"}, {"word": "honey", "gender": "female"}, {"word": "corsages", "gender": "female"}, {"word": "camellias", "gender": "female"}, {"word": "impregnation", "gender": "female"}, {"word": "enchantress", "gender": "female"}, {"word": "inhabitants", "gender": "female"}, {"word": "braids", "gender": "female"}, {"word": "deli", "gender": "female"}, {"word": "sixties", "gender": "female"}, {"word": "beach", "gender": "female"}, {"word": "becky", "gender": "female"}, {"word": "elizabeth", "gender": "female"}, {"word": "beauty", "gender": "female"}, {"word": "abdomen", "gender": "female"}, {"word": "mouflon", "gender": "female"}, {"word": "forewoman", "gender": "female"}, {"word": "schoolchildren", "gender": "female"}, {"word": "lesbian", "gender": "female"}, {"word": "demoness", "gender": "female"}, {"word": "calves", "gender": "female"}, {"word": "assemblywoman", "gender": "female"}, {"word": "nympho", "gender": "female"}, {"word": "allison", "gender": "female"}, {"word": "belle", "gender": "female"}, {"word": "athletes", "gender": "female"}, {"word": "apse", "gender": "female"}, {"word": "schoolmates", "gender": "female"}, {"word": "modesty", "gender": "female"}, {"word": "fetus", "gender": "female"}, {"word": "office", "gender": "female"}, {"word": "consent", "gender": "female"}, {"word": "hairnet", "gender": "female"}, {"word": "mallard", "gender": "female"}, {"word": "househusband", "gender": "female"}, {"word": "reformers", "gender": "female"}, {"word": "castes", "gender": "female"}, {"word": "adolescence", "gender": "female"}, {"word": "womanhood", "gender": "female"}, {"word": "survivors", "gender": "female"}, {"word": "tramp", "gender": "female"}, {"word": "fig", "gender": "female"}, {"word": "enlistee", "gender": "female"}, {"word": "them", "gender": "female"}, {"word": "sterilization", "gender": "female"}, {"word": "chatelaine", "gender": "female"}, {"word": "detachment", "gender": "female"}, {"word": "scholar", "gender": "female"}, {"word": "meat", "gender": "female"}, {"word": "mayoress", "gender": "female"}, {"word": "lucy", "gender": "female"}, {"word": "alexis", "gender": "female"}, {"word": "choir", "gender": "female"}, {"word": "alexia", "gender": "female"}, {"word": "clavicle", "gender": "female"}, {"word": "burial", "gender": "female"}, {"word": "chiffon", "gender": "female"}, {"word": "diana", "gender": "female"}, {"word": "garment", "gender": "female"}, {"word": "masseuse", "gender": "female"}, {"word": "aide", "gender": "female"}, {"word": "danseuse", "gender": "female"}, {"word": "member", "gender": "female"}, {"word": "seductress", "gender": "female"}, {"word": "navy", "gender": "female"}, {"word": "businesswomen", "gender": "female"}, {"word": "hostel", "gender": "female"}, {"word": "babirusa", "gender": "female"}, {"word": "tanners", "gender": "female"}, {"word": "reader", "gender": "female"}, {"word": "aja", "gender": "female"}, {"word": "hooker", "gender": "female"}, {"word": "nightdress", "gender": "female"}, {"word": "intersex", "gender": "female"}, {"word": "negligee", "gender": "female"}, {"word": "ladylove", "gender": "female"}, {"word": "aboriginal", "gender": "female"}, {"word": "counterparts", "gender": "female"}, {"word": "mistress", "gender": "female"}, {"word": "storm", "gender": "female"}, {"word": "aisle", "gender": "female"}, {"word": "saggy", "gender": "female"}, {"word": "oviduct", "gender": "female"}, {"word": "bakla", "gender": "female"}, {"word": "refugee", "gender": "female"}, {"word": "louse", "gender": "female"}, {"word": "smokers", "gender": "female"}, {"word": "grownups", "gender": "female"}, {"word": "buttock", "gender": "female"}, {"word": "chaffinch", "gender": "female"}, {"word": "olds", "gender": "female"}, {"word": "basketball", "gender": "female"}, {"word": "seduction", "gender": "female"}, {"word": "girls", "gender": "female"}, {"word": "tot", "gender": "female"}, {"word": "twenties", "gender": "female"}, {"word": "signor", "gender": "female"}, {"word": "burgess", "gender": "female"}, {"word": "dogs", "gender": "female"}, {"word": "western", "gender": "female"}, {"word": "majorette", "gender": "female"}, {"word": "radiograph", "gender": "female"}, {"word": "bindi", "gender": "female"}, {"word": "femaleness", "gender": "female"}, {"word": "demoiselle", "gender": "female"}, {"word": "hottie", "gender": "female"}, {"word": "fishwife", "gender": "female"}, {"word": "seminary", "gender": "female"}, {"word": "countess", "gender": "female"}, {"word": "corroboree", "gender": "female"}, {"word": "fashion", "gender": "female"}, {"word": "handkerchief", "gender": "female"}, {"word": "runner", "gender": "female"}, {"word": "dildo", "gender": "female"}, {"word": "minx", "gender": "female"}, {"word": "seamstress", "gender": "female"}, {"word": "menarche", "gender": "female"}, {"word": "dozen", "gender": "female"}, {"word": "hymen", "gender": "female"}, {"word": "capuchin", "gender": "female"}, {"word": "snow", "gender": "female"}, {"word": "cotillion", "gender": "female"}, {"word": "subjects", "gender": "female"}, {"word": "pinafore", "gender": "female"}, {"word": "niece", "gender": "female"}, {"word": "panties", "gender": "female"}, {"word": "matriarch", "gender": "female"}, {"word": "maiden", "gender": "female"}, {"word": "jurisconsult", "gender": "female"}, {"word": "anatomy", "gender": "female"}, {"word": "coif", "gender": "female"}, {"word": "pantsuit", "gender": "female"}, {"word": "osteoporosis", "gender": "female"}, {"word": "genital", "gender": "female"}, {"word": "sedan", "gender": "female"}, {"word": "grave", "gender": "female"}, {"word": "prostitute", "gender": "female"}, {"word": "singer", "gender": "female"}, {"word": "alumna", "gender": "female"}, {"word": "dog", "gender": "female"}, {"word": "doe", "gender": "female"}, {"word": "doy", "gender": "female"}, {"word": "aunt", "gender": "female"}, {"word": "boyfriends", "gender": "female"}, {"word": "mating", "gender": "female"}, {"word": "prim", "gender": "female"}, {"word": "seducer", "gender": "female"}, {"word": "pope", "gender": "female"}, {"word": "dames", "gender": "female"}, {"word": "visitor", "gender": "female"}, {"word": "queen", "gender": "female"}, {"word": "bimbo", "gender": "female"}, {"word": "cancan", "gender": "female"}, {"word": "sexism", "gender": "female"}, {"word": "termagant", "gender": "female"}, {"word": "eider", "gender": "female"}, {"word": "feminization", "gender": "female"}, {"word": "divinity", "gender": "female"}, {"word": "objectification", "gender": "female"}, {"word": "busk", "gender": "female"}, {"word": "population", "gender": "female"}, {"word": "bubblehead", "gender": "female"}, {"word": "machos", "gender": "female"}, {"word": "gogo", "gender": "female"}, {"word": "amazon", "gender": "female"}, {"word": "roundabout", "gender": "female"}, {"word": "wedding", "gender": "female"}, {"word": "peacock", "gender": "female"}, {"word": "diethylstilbestrol", "gender": "female"}, {"word": "boarder", "gender": "female"}, {"word": "suffrage", "gender": "female"}, {"word": "fertility", "gender": "female"}, {"word": "frigidity", "gender": "female"}, {"word": "dower", "gender": "female"}, {"word": "elopement", "gender": "female"}, {"word": "human", "gender": "female"}, {"word": "gymslip", "gender": "female"}, {"word": "nun", "gender": "female"}, {"word": "allure", "gender": "female"}, {"word": "sakti", "gender": "female"}, {"word": "juliet", "gender": "female"}, {"word": "shakti", "gender": "female"}, {"word": "clitoridectomy", "gender": "female"}, {"word": "grandmother", "gender": "female"}, {"word": "sista", "gender": "female"}, {"word": "shaver", "gender": "female"}, {"word": "gays", "gender": "female"}, {"word": "beautician", "gender": "female"}, {"word": "debs", "gender": "female"}, {"word": "bras", "gender": "female"}, {"word": "goddess", "gender": "female"}, {"word": "frump", "gender": "female"}, {"word": "cow", "gender": "female"}, {"word": "bachelorette", "gender": "female"}, {"word": "impala", "gender": "female"}, {"word": "damsels", "gender": "female"}, {"word": "matrimony", "gender": "female"}, {"word": "cob", "gender": "female"}, {"word": "dora", "gender": "female"}, {"word": "equalitarian", "gender": "female"}, {"word": "blonds", "gender": "female"}, {"word": "hers", "gender": "female"}, {"word": "camisa", "gender": "female"}, {"word": "basque", "gender": "female"}, {"word": "pregnancy", "gender": "female"}, {"word": "blonde", "gender": "female"}, {"word": "mannish", "gender": "female"}, {"word": "ayah", "gender": "female"}, {"word": "bikinis", "gender": "female"}, {"word": "privilege", "gender": "female"}, {"word": "captives", "gender": "female"}, {"word": "lovely", "gender": "female"}, {"word": "castration", "gender": "female"}, {"word": "spermatozoon", "gender": "female"}, {"word": "families", "gender": "female"}, {"word": "worker", "gender": "female"}, {"word": "bladder", "gender": "female"}, {"word": "child", "gender": "female"}, {"word": "cunt", "gender": "female"}, {"word": "physician", "gender": "female"}, {"word": "concubinage", "gender": "female"}, {"word": "chauvinist", "gender": "female"}, {"word": "presidency", "gender": "female"}, {"word": "chevalier", "gender": "female"}, {"word": "serai", "gender": "female"}, {"word": "voice", "gender": "female"}, {"word": "davenport", "gender": "female"}, {"word": "chauvinism", "gender": "female"}, {"word": "skirts", "gender": "female"}, {"word": "kohl", "gender": "female"}, {"word": "madonna", "gender": "female"}, {"word": "mouse", "gender": "female"}, {"word": "descent", "gender": "female"}, {"word": "parish", "gender": "female"}, {"word": "bedchamber", "gender": "female"}, {"word": "bella", "gender": "female"}, {"word": "belly", "gender": "female"}, {"word": "babies", "gender": "female"}, {"word": "esquire", "gender": "female"}, {"word": "bunny", "gender": "female"}, {"word": "moose", "gender": "female"}, {"word": "mujeres", "gender": "female"}, {"word": "ella", "gender": "female"}, {"word": "workforce", "gender": "female"}, {"word": "elle", "gender": "female"}, {"word": "landman", "gender": "female"}, {"word": "waterfall", "gender": "female"}, {"word": "characters", "gender": "female"}, {"word": "unicorn", "gender": "female"}, {"word": "wives", "gender": "female"}, {"word": "tassel", "gender": "female"}, {"word": "knockoff", "gender": "female"}, {"word": "noblewoman", "gender": "female"}, {"word": "sweetness", "gender": "female"}, {"word": "mammy", "gender": "female"}, {"word": "smoker", "gender": "female"}, {"word": "client", "gender": "female"}, {"word": "mamma", "gender": "female"}, {"word": "mother", "gender": "female"}, {"word": "milliner", "gender": "female"}, {"word": "spencer", "gender": "female"}, {"word": "dads", "gender": "female"}, {"word": "gigolo", "gender": "female"}, {"word": "unemployment", "gender": "female"}, {"word": "photo", "gender": "female"}, {"word": "grader", "gender": "female"}, {"word": "celandine", "gender": "female"}, {"word": "victim", "gender": "female"}, {"word": "plight", "gender": "female"}, {"word": "stepdaughter", "gender": "female"}, {"word": "cervix", "gender": "female"}, {"word": "brassiere", "gender": "female"}, {"word": "occupants", "gender": "female"}, {"word": "hag", "gender": "female"}, {"word": "ewes", "gender": "female"}, {"word": "ma'am", "gender": "female"}, {"word": "hypospadias", "gender": "female"}, {"word": "east", "gender": "female"}, {"word": "actresses", "gender": "female"}, {"word": "scrotum", "gender": "female"}, {"word": "sailors", "gender": "female"}, {"word": "advances", "gender": "female"}, {"word": "birth", "gender": "female"}, {"word": "judge", "gender": "female"}, {"word": "burns", "gender": "female"}, {"word": "dreams", "gender": "female"}, {"word": "vanity", "gender": "female"}, {"word": "dignity", "gender": "female"}, {"word": "gift", "gender": "female"}, {"word": "nude", "gender": "female"}, {"word": "alice", "gender": "female"}, {"word": "banshee", "gender": "female"}, {"word": "officer", "gender": "female"}, {"word": "bodkin", "gender": "female"}, {"word": "amor", "gender": "female"}, {"word": "clementine", "gender": "female"}, {"word": "antique", "gender": "female"}, {"word": "dean", "gender": "female"}, {"word": "stereotype", "gender": "female"}, {"word": "people", "gender": "female"}, {"word": "born", "gender": "female"}, {"word": "couture", "gender": "female"}, {"word": "danseur", "gender": "female"}, {"word": "nobleman", "gender": "female"}, {"word": "incontinence", "gender": "female"}, {"word": "climacteric", "gender": "female"}, {"word": "companions", "gender": "female"}, {"word": "bra", "gender": "female"}, {"word": "bullfight", "gender": "female"}, {"word": "scoter", "gender": "female"}, {"word": "rep", "gender": "female"}, {"word": "erotics", "gender": "female"}, {"word": "blackmail", "gender": "female"}, {"word": "graduates", "gender": "female"}, {"word": "menopause", "gender": "female"}, {"word": "tribes", "gender": "female"}, {"word": "empowerment", "gender": "female"}, {"word": "sportswomen", "gender": "female"}, {"word": "citizens", "gender": "female"}, {"word": "anima", "gender": "female"}, {"word": "prisoners", "gender": "female"}, {"word": "chimp", "gender": "female"}, {"word": "fern", "gender": "female"}, {"word": "emancipation", "gender": "female"}, {"word": "laborers", "gender": "female"}, {"word": "sow", "gender": "female"}, {"word": "petting", "gender": "female"}, {"word": "coitus", "gender": "female"}, {"word": "mullah", "gender": "female"}, {"word": "sculptress", "gender": "female"}, {"word": "merkin", "gender": "female"}, {"word": "virgin", "gender": "female"}, {"word": "crews", "gender": "female"}, {"word": "jane", "gender": "female"}, {"word": "bobolink", "gender": "female"}, {"word": "grooms", "gender": "female"}, {"word": "preschoolers", "gender": "female"}, {"word": "feminine", "gender": "female"}, {"word": "bighorn", "gender": "female"}, {"word": "nursemaid", "gender": "female"}, {"word": "dowry", "gender": "female"}, {"word": "extremity", "gender": "female"}, {"word": "bailment", "gender": "female"}, {"word": "womanliness", "gender": "female"}, {"word": "basilica", "gender": "female"}, {"word": "blackcap", "gender": "female"}, {"word": "nudity", "gender": "female"}, {"word": "evidence", "gender": "female"}, {"word": "kaftan", "gender": "female"}, {"word": "moll", "gender": "female"}, {"word": "mrs", "gender": "female"}, {"word": "equestrienne", "gender": "female"}, {"word": "courtesan", "gender": "female"}, {"word": "madwoman", "gender": "female"}, {"word": "dying", "gender": "female"}, {"word": "foremother", "gender": "female"}, {"word": "herstory", "gender": "female"}, {"word": "countrywoman", "gender": "female"}, {"word": "chauvinists", "gender": "female"}, {"word": "holly", "gender": "female"}, {"word": "tess", "gender": "female"}, {"word": "picture", "gender": "female"}, {"word": "girlishness", "gender": "female"}, {"word": "ovaries", "gender": "female"}, {"word": "troupe", "gender": "female"}, {"word": "boudoir", "gender": "female"}, {"word": "signora", "gender": "female"}, {"word": "gorilla", "gender": "female"}, {"word": "gonorrhea", "gender": "female"}, {"word": "gown", "gender": "female"}, {"word": "milt", "gender": "female"}, {"word": "matron", "gender": "female"}, {"word": "dance", "gender": "female"}, {"word": "skit", "gender": "female"}, {"word": "laura", "gender": "female"}, {"word": "burqa", "gender": "female"}, {"word": "colleen", "gender": "female"}, {"word": "chair", "gender": "female"}, {"word": "milk", "gender": "female"}, {"word": "ballet", "gender": "female"}, {"word": "jogger", "gender": "female"}, {"word": "manicurist", "gender": "female"}, {"word": "poetess", "gender": "female"}, {"word": "adjudicator", "gender": "female"}, {"word": "tanka", "gender": "female"}, {"word": "fob", "gender": "female"}, {"word": "jezebel", "gender": "female"}, {"word": "zhang", "gender": "female"}, {"word": "hannah", "gender": "female"}, {"word": "tupuna", "gender": "female"}, {"word": "congregation", "gender": "female"}, {"word": "alcoholics", "gender": "female"}, {"word": "kitten", "gender": "female"}, {"word": "cook", "gender": "female"}, {"word": "bartender", "gender": "female"}, {"word": "lohan", "gender": "female"}, {"word": "die", "gender": "female"}, {"word": "levee", "gender": "female"}, {"word": "brothel", "gender": "female"}, {"word": "teal", "gender": "female"}, {"word": "yale", "gender": "female"}, {"word": "gentlewoman", "gender": "female"}, {"word": "malu", "gender": "female"}, {"word": "pregnancies", "gender": "female"}, {"word": "bf", "gender": "female"}, {"word": "dorothy", "gender": "female"}, {"word": "fear", "gender": "female"}, {"word": "nightie", "gender": "female"}, {"word": "odalisque", "gender": "female"}, {"word": "constitution", "gender": "female"}, {"word": "filles", "gender": "female"}, {"word": "spire", "gender": "female"}, {"word": "axel", "gender": "female"}, {"word": "camisole", "gender": "female"}, {"word": "muslin", "gender": "female"}, {"word": "guardian", "gender": "female"}, {"word": "clerk", "gender": "female"}, {"word": "stallion", "gender": "female"}, {"word": "femininity", "gender": "female"}, {"word": "tailcoat", "gender": "female"}, {"word": "witch", "gender": "female"}, {"word": "alone", "gender": "female"}, {"word": "teacher", "gender": "female"}, {"word": "molestation", "gender": "female"}, {"word": "passengers", "gender": "female"}, {"word": "parasol", "gender": "female"}, {"word": "celibates", "gender": "female"}, {"word": "carmel", "gender": "female"}, {"word": "prude", "gender": "female"}, {"word": "boa", "gender": "female"}, {"word": "recantation", "gender": "female"}, {"word": "bod", "gender": "female"}, {"word": "teenage", "gender": "female"}, {"word": "love", "gender": "female"}, {"word": "tuxedo", "gender": "female"}, {"word": "horses", "gender": "female"}, {"word": "pony", "gender": "female"}, {"word": "contessa", "gender": "female"}, {"word": "sisterly", "gender": "female"}, {"word": "shopgirl", "gender": "female"}, {"word": "sonnets", "gender": "female"}, {"word": "angels", "gender": "female"}, {"word": "altar", "gender": "female"}, {"word": "oestrus", "gender": "female"}, {"word": "bellman", "gender": "female"}, {"word": "osprey", "gender": "female"}, {"word": "riders", "gender": "female"}, {"word": "migrants", "gender": "female"}, {"word": "flagellum", "gender": "female"}, {"word": "moccasin", "gender": "female"}, {"word": "milady", "gender": "female"}, {"word": "chignon", "gender": "female"}, {"word": "abortion", "gender": "female"}, {"word": "cat", "gender": "female"}, {"word": "cab", "gender": "female"}, {"word": "androsterone", "gender": "female"}, {"word": "cad", "gender": "female"}, {"word": "chadar", "gender": "female"}, {"word": "chit", "gender": "female"}, {"word": "avocation", "gender": "female"}, {"word": "bridesmaid", "gender": "female"}, {"word": "schoolgirl", "gender": "female"}, {"word": "council", "gender": "female"}, {"word": "pink", "gender": "female"}, {"word": "complainant", "gender": "female"}, {"word": "kaffiyeh", "gender": "female"}, {"word": "inheritance", "gender": "female"}, {"word": "cardinal", "gender": "female"}, {"word": "pederasty", "gender": "female"}, {"word": "trollop", "gender": "female"}, {"word": "granddaughter", "gender": "female"}, {"word": "southern", "gender": "female"}, {"word": "diva", "gender": "female"}, {"word": "accessory", "gender": "female"}, {"word": "exhibitionist", "gender": "female"}, {"word": "mam", "gender": "female"}, {"word": "murderess", "gender": "female"}, {"word": "waist", "gender": "female"}, {"word": "gorget", "gender": "female"}, {"word": "wheelchair", "gender": "female"}, {"word": "applicant", "gender": "female"}, {"word": "beehive", "gender": "female"}, {"word": "obverse", "gender": "female"}, {"word": "basket", "gender": "female"}, {"word": "representation", "gender": "female"}, {"word": "guttersnipe", "gender": "female"}, {"word": "houseboy", "gender": "female"}, {"word": "colt", "gender": "female"}, {"word": "garrison", "gender": "female"}, {"word": "goldfinch", "gender": "female"}, {"word": "arabesque", "gender": "female"}, {"word": "owl", "gender": "female"}, {"word": "carapace", "gender": "female"}, {"word": "group", "gender": "female"}, {"word": "heterosexism", "gender": "female"}, {"word": "nymph", "gender": "female"}, {"word": "cheerleaders", "gender": "female"}, {"word": "curls", "gender": "female"}, {"word": "lavalava", "gender": "female"}, {"word": "maid", "gender": "female"}, {"word": "tiara", "gender": "female"}, {"word": "priesthood", "gender": "female"}, {"word": "workingwoman", "gender": "female"}, {"word": "apron", "gender": "female"}, {"word": "moms", "gender": "female"}, {"word": "charring", "gender": "female"}, {"word": "cuckoldry", "gender": "female"}, {"word": "barrow", "gender": "female"}, {"word": "equality", "gender": "female"}, {"word": "airman", "gender": "female"}, {"word": "peasant", "gender": "female"}, {"word": "broodmare", "gender": "female"}, {"word": "subjection", "gender": "female"}, {"word": "saleslady", "gender": "female"}, {"word": "shirtwaist", "gender": "female"}, {"word": "gamine", "gender": "female"}, {"word": "begum", "gender": "female"}, {"word": "mohel", "gender": "female"}, {"word": "hinny", "gender": "female"}, {"word": "girl", "gender": "female"}, {"word": "karyotype", "gender": "female"}, {"word": "living", "gender": "female"}, {"word": "afghans", "gender": "female"}, {"word": "intercourse", "gender": "female"}, {"word": "perineum", "gender": "female"}, {"word": "housemaid", "gender": "female"}, {"word": "grecian", "gender": "female"}, {"word": "nudes", "gender": "female"}, {"word": "nautch", "gender": "female"}, {"word": "eagle", "gender": "female"}, {"word": "booby", "gender": "female"}, {"word": "hairdresser", "gender": "female"}, {"word": "froufrou", "gender": "female"}, {"word": "cart", "gender": "female"}, {"word": "grandma", "gender": "female"}, {"word": "buckskin", "gender": "female"}, {"word": "manikin", "gender": "female"}, {"word": "roosters", "gender": "female"}, {"word": "language", "gender": "female"}, {"word": "teachers", "gender": "female"}, {"word": "monsignor", "gender": "female"}, {"word": "bisexuality", "gender": "female"}, {"word": "mothering", "gender": "female"}, {"word": "coeducation", "gender": "female"}, {"word": "cellulite", "gender": "female"}, {"word": "childhood", "gender": "female"}, {"word": "blind", "gender": "female"}, {"word": "rebozo", "gender": "female"}, {"word": "nativity", "gender": "female"}, {"word": "twinkie", "gender": "female"}, {"word": "hairdressers", "gender": "female"}, {"word": "creche", "gender": "female"}, {"word": "sheep", "gender": "female"}, {"word": "convent", "gender": "female"}, {"word": "plastic", "gender": "female"}, {"word": "prioress", "gender": "female"}, {"word": "chastity", "gender": "female"}, {"word": "escort", "gender": "female"}, {"word": "white", "gender": "female"}, {"word": "mermaid", "gender": "female"}, {"word": "cutty", "gender": "female"}, {"word": "amaryllis", "gender": "female"}, {"word": "shawl", "gender": "female"}, {"word": "men's", "gender": "female"}, {"word": "artifact", "gender": "female"}, {"word": "cheerleading", "gender": "female"}, {"word": "inmates", "gender": "female"}, {"word": "flowers", "gender": "female"}, {"word": "boyfriend", "gender": "female"}, {"word": "relative", "gender": "female"}, {"word": "spokeswoman", "gender": "female"}, {"word": "mutilation", "gender": "female"}, {"word": "bootee", "gender": "female"}, {"word": "angel", "gender": "female"}, {"word": "suffragette", "gender": "female"}, {"word": "briefs", "gender": "female"}, {"word": "prostitution", "gender": "female"}, {"word": "voices", "gender": "female"}, {"word": "balsam", "gender": "female"}, {"word": "borough", "gender": "female"}, {"word": "squaw", "gender": "female"}, {"word": "handicraft", "gender": "female"}, {"word": "dirndl", "gender": "female"}, {"word": "somethings", "gender": "female"}, {"word": "maulvi", "gender": "female"}, {"word": "sorority", "gender": "female"}, {"word": "cheesecake", "gender": "female"}, {"word": "tract", "gender": "female"}, {"word": "freshman", "gender": "female"}, {"word": "beth", "gender": "female"}, {"word": "bluebird", "gender": "female"}, {"word": "highboy", "gender": "female"}, {"word": "farmers", "gender": "female"}, {"word": "constable", "gender": "female"}, {"word": "filly", "gender": "female"}, {"word": "tooth", "gender": "female"}, {"word": "fille", "gender": "female"}, {"word": "slaves", "gender": "female"}, {"word": "ordination", "gender": "female"}, {"word": "landlady", "gender": "female"}, {"word": "shop", "gender": "female"}, {"word": "goddaughter", "gender": "female"}, {"word": "cloaca", "gender": "female"}, {"word": "salon", "gender": "female"}, {"word": "therapist", "gender": "female"}, {"word": "ladybird", "gender": "female"}, {"word": "androgyne", "gender": "female"}, {"word": "title", "gender": "female"}, {"word": "proportion", "gender": "female"}, {"word": "distaff", "gender": "female"}, {"word": "liberation", "gender": "female"}, {"word": "black", "gender": "female"}, {"word": "caroline", "gender": "female"}, {"word": "crimper", "gender": "female"}, {"word": "fifties", "gender": "female"}, {"word": "helpmeet", "gender": "female"}, {"word": "bittern", "gender": "female"}, {"word": "hostage", "gender": "female"}, {"word": "shiksa", "gender": "female"}, {"word": "clerks", "gender": "female"}, {"word": "primates", "gender": "female"}, {"word": "golliwog", "gender": "female"}, {"word": "businesswoman", "gender": "female"}, {"word": "orphans", "gender": "female"}, {"word": "breeches", "gender": "female"}, {"word": "priest", "gender": "female"}, {"word": "demimonde", "gender": "female"}, {"word": "pants", "gender": "female"}, {"word": "husband", "gender": "female"}, {"word": "executrix", "gender": "female"}, {"word": "starlet", "gender": "female"}, {"word": "heifers", "gender": "female"}, {"word": "erica", "gender": "female"}, {"word": "cadets", "gender": "female"}, {"word": "gantlet", "gender": "female"}, {"word": "bicyclist", "gender": "female"}, {"word": "dormitory", "gender": "female"}, {"word": "chimpanzees", "gender": "female"}, {"word": "teens", "gender": "female"}, {"word": "tux", "gender": "female"}, {"word": "parent", "gender": "female"}, {"word": "policewomen", "gender": "female"}, {"word": "spitfire", "gender": "female"}, {"word": "singers", "gender": "female"}, {"word": "article", "gender": "female"}, {"word": "tub", "gender": "female"}, {"word": "childbirth", "gender": "female"}, {"word": "kirsten", "gender": "female"}, {"word": "elders", "gender": "female"}, {"word": "sunbather", "gender": "female"}, {"word": "pantaloon", "gender": "female"}, {"word": "manx", "gender": "female"}, {"word": "priestess", "gender": "female"}, {"word": "patrons", "gender": "female"}, {"word": "workplace", "gender": "female"}, {"word": "senator", "gender": "female"}, {"word": "cancer", "gender": "female"}, {"word": "color", "gender": "female"}, {"word": "jeans", "gender": "female"}, {"word": "juvenile", "gender": "female"}, {"word": "homosexuality", "gender": "female"}, {"word": "mulatto", "gender": "female"}, {"word": "womenfolk", "gender": "female"}, {"word": "perpetrators", "gender": "female"}, {"word": "pigtails", "gender": "female"}, {"word": "custody", "gender": "female"}, {"word": "estrogen", "gender": "female"}, {"word": "mare", "gender": "female"}, {"word": "scrunchie", "gender": "female"}, {"word": "companionship", "gender": "female"}, {"word": "lioness", "gender": "female"}, {"word": "teddy", "gender": "female"}, {"word": "gynecomastia", "gender": "female"}, {"word": "west", "gender": "female"}, {"word": "coupe", "gender": "female"}, {"word": "petit", "gender": "female"}, {"word": "hubbies", "gender": "female"}, {"word": "sisterhood", "gender": "female"}, {"word": "mary", "gender": "female"}, {"word": "purdah", "gender": "female"}, {"word": "taffeta", "gender": "female"}, {"word": "photos", "gender": "female"}, {"word": "concubine", "gender": "female"}, {"word": "hypogonadism", "gender": "female"}, {"word": "gland", "gender": "female"}, {"word": "conception", "gender": "female"}, {"word": "cherub", "gender": "female"}, {"word": "fetuses", "gender": "female"}, {"word": "canoe", "gender": "female"}, {"word": "purse", "gender": "female"}, {"word": "couples", "gender": "female"}, {"word": "stewardess", "gender": "female"}, {"word": "hijab", "gender": "female"}, {"word": "hermaphrodite", "gender": "female"}, {"word": "hens", "gender": "female"}, {"word": "tchotchke", "gender": "female"}, {"word": "schoolmistress", "gender": "female"}, {"word": "widows", "gender": "female"}, {"word": "doctor", "gender": "female"}, {"word": "gelding", "gender": "female"}, {"word": "fatima", "gender": "female"}, {"word": "figurine", "gender": "female"}, {"word": "macaroni", "gender": "female"}, {"word": "coworkers", "gender": "female"}, {"word": "document", "gender": "female"}, {"word": "homophobia", "gender": "female"}, {"word": "isle", "gender": "female"}, {"word": "nest", "gender": "female"}, {"word": "refusal", "gender": "female"}, {"word": "births", "gender": "female"}, {"word": "companion", "gender": "female"}, {"word": "persons", "gender": "female"}, {"word": "petticoat", "gender": "female"}, {"word": "fruit", "gender": "female"}, {"word": "vocalist", "gender": "female"}, {"word": "escorts", "gender": "female"}, {"word": "gamin", "gender": "female"}, {"word": "constitutional", "gender": "female"}, {"word": "wedge", "gender": "female"}, {"word": "nocturia", "gender": "female"}, {"word": "cialis", "gender": "female"}, {"word": "hysterectomies", "gender": "female"}, {"word": "playsuit", "gender": "female"}, {"word": "aunty", "gender": "female"}, {"word": "dancers", "gender": "female"}, {"word": "kilt", "gender": "female"}, {"word": "actress", "gender": "female"}, {"word": "chador", "gender": "female"}, {"word": "maternity", "gender": "female"}, {"word": "vamp", "gender": "female"}, {"word": "satin", "gender": "female"}, {"word": "blondes", "gender": "female"}, {"word": "socialite", "gender": "female"}, {"word": "death", "gender": "female"}, {"word": "feminist", "gender": "female"}, {"word": "pups", "gender": "female"}, {"word": "regent", "gender": "female"}, {"word": "nymphomaniac", "gender": "female"}, {"word": "countrywomen", "gender": "female"}, {"word": "feminism", "gender": "female"}, {"word": "bedstraw", "gender": "female"}, {"word": "bluestocking", "gender": "female"}, {"word": "amy", "gender": "female"}, {"word": "mom", "gender": "female"}, {"word": "lady", "gender": "female"}, {"word": "parliamentarians", "gender": "female"}, {"word": "bracelet", "gender": "female"}, {"word": "homegirl", "gender": "female"}, {"word": "morena", "gender": "female"}, {"word": "kennel", "gender": "female"}, {"word": "maids", "gender": "female"}, {"word": "doll", "gender": "female"}, {"word": "complementarity", "gender": "female"}, {"word": "divine", "gender": "female"}, {"word": "joan", "gender": "female"}, {"word": "sunbird", "gender": "female"}, {"word": "mandrake", "gender": "female"}, {"word": "tots", "gender": "female"}, {"word": "ellie", "gender": "female"}, {"word": "babysitter", "gender": "female"}, {"word": "boat", "gender": "female"}, {"word": "songstress", "gender": "female"}, {"word": "compulsion", "gender": "female"}, {"word": "preadolescent", "gender": "female"}, {"word": "ovulation", "gender": "female"}, {"word": "jabot", "gender": "female"}, {"word": "wimmin", "gender": "female"}, {"word": "pooch", "gender": "female"}, {"word": "senora", "gender": "female"}, {"word": "innocence", "gender": "female"}, {"word": "endogamy", "gender": "female"}, {"word": "kindergartener", "gender": "female"}, {"word": "stereotypes", "gender": "female"}, {"word": "kindergartners", "gender": "female"}, {"word": "disabilities", "gender": "female"}, {"word": "violence", "gender": "female"}, {"word": "aboriginals", "gender": "female"}, {"word": "helpmate", "gender": "female"}, {"word": "parson", "gender": "female"}, {"word": "neighbor", "gender": "female"}, {"word": "pieta", "gender": "female"}, {"word": "tribe", "gender": "female"}, {"word": "ladies", "gender": "female"}, {"word": "chivalry", "gender": "female"}, {"word": "hypermasculine", "gender": "female"}, {"word": "whites", "gender": "female"}, {"word": "image", "gender": "female"}, {"word": "empress", "gender": "female"}, {"word": "wilde", "gender": "female"}, {"word": "elementary", "gender": "female"}, {"word": "portrayal", "gender": "female"}, {"word": "knickerbocker", "gender": "female"}, {"word": "pleasantry", "gender": "female"}, {"word": "her", "gender": "female"}, {"word": "unisex", "gender": "female"}, {"word": "trapeze", "gender": "female"}, {"word": "babushka", "gender": "female"}, {"word": "cats", "gender": "female"}, {"word": "missy", "gender": "female"}, {"word": "expatriate", "gender": "female"}, {"word": "hen", "gender": "female"}, {"word": "soprano", "gender": "female"}, {"word": "housewives", "gender": "female"}, {"word": "terminus", "gender": "female"}, {"word": "ambassadress", "gender": "female"}, {"word": "flirt", "gender": "female"}, {"word": "strawberry", "gender": "female"}, {"word": "preteens", "gender": "female"}, {"word": "reprimand", "gender": "female"}, {"word": "midwife", "gender": "female"}, {"word": "girlfriend", "gender": "female"}, {"word": "politics", "gender": "female"}, {"word": "dreamgirl", "gender": "female"}, {"word": "horse", "gender": "female"}, {"word": "bishop", "gender": "female"}, {"word": "cream", "gender": "female"}, {"word": "fiddler", "gender": "female"}, {"word": "yoga", "gender": "female"}, {"word": "drivers", "gender": "female"}, {"word": "roses", "gender": "female"}, {"word": "housework", "gender": "female"}, {"word": "trash", "gender": "female"}, {"word": "passerby", "gender": "female"}, {"word": "classmate", "gender": "female"}, {"word": "students", "gender": "female"}, {"word": "cove", "gender": "female"}, {"word": "lovers", "gender": "female"}, {"word": "authoress", "gender": "female"}, {"word": "spouse", "gender": "female"}, {"word": "temptress", "gender": "female"}, {"word": "wife", "gender": "female"}, {"word": "oriole", "gender": "female"}, {"word": "sidesaddle", "gender": "female"}, {"word": "caste", "gender": "female"}, {"word": "homes", "gender": "female"}, {"word": "skeleton", "gender": "female"}, {"word": "katy", "gender": "female"}, {"word": "alb", "gender": "female"}, {"word": "welfare", "gender": "female"}, {"word": "brunettes", "gender": "female"}, {"word": "mommies", "gender": "female"}, {"word": "children", "gender": "female"}, {"word": "emily", "gender": "female"}, {"word": "garibaldi", "gender": "female"}, {"word": "apartment", "gender": "female"}, {"word": "minyan", "gender": "female"}, {"word": "siblings", "gender": "female"}, {"word": "woman", "gender": "female"}, {"word": "song", "gender": "female"}, {"word": "hitchhiker", "gender": "female"}, {"word": "eldest", "gender": "female"}, {"word": "liger", "gender": "female"}, {"word": "diary", "gender": "female"}, {"word": "nuns", "gender": "female"}, {"word": "elena", "gender": "female"}, {"word": "pillbox", "gender": "female"}, {"word": "mothers", "gender": "female"}, {"word": "celebrity", "gender": "female"}, {"word": "lesbians", "gender": "female"}, {"word": "alms", "gender": "female"}, {"word": "wallflower", "gender": "female"}, {"word": "neighborhood", "gender": "female"}, {"word": "orgasm", "gender": "female"}, {"word": "rate", "gender": "female"}, {"word": "bloomers", "gender": "female"}, {"word": "reine", "gender": "female"}, {"word": "gonad", "gender": "female"}, {"word": "everywoman", "gender": "female"}, {"word": "nana", "gender": "female"}, {"word": "cohabitation", "gender": "female"}, {"word": "coroner", "gender": "female"}, {"word": "nurse", "gender": "female"}, {"word": "microchip", "gender": "female"}, {"word": "musth", "gender": "female"}, {"word": "womb", "gender": "female"}, {"word": "gametophyte", "gender": "female"}, {"word": "hours", "gender": "female"}, {"word": "harridan", "gender": "female"}, {"word": "bulls", "gender": "female"}, {"word": "fantasies", "gender": "female"}, {"word": "patriarchate", "gender": "female"}, {"word": "heifer", "gender": "female"}, {"word": "drawers", "gender": "female"}, {"word": "mantilla", "gender": "female"}, {"word": "cathy", "gender": "female"}, {"word": "anthurium", "gender": "female"}, {"word": "estrus", "gender": "female"}, {"word": "family", "gender": "female"}, {"word": "marriages", "gender": "female"}, {"word": "chorine", "gender": "female"}, {"word": "captor", "gender": "female"}, {"word": "psittacosis", "gender": "female"}, {"word": "tragopan", "gender": "female"}, {"word": "gosh", "gender": "female"}, {"word": "epaulette", "gender": "female"}, {"word": "dowager", "gender": "female"}, {"word": "libertine", "gender": "female"}, {"word": "harlequin", "gender": "female"}, {"word": "rustic", "gender": "female"}, {"word": "lassie", "gender": "female"}, {"word": "hegemony", "gender": "female"}, {"word": "metis", "gender": "female"}, {"word": "teen", "gender": "female"}, {"word": "ladybug", "gender": "female"}, {"word": "testes", "gender": "female"}, {"word": "cheongsam", "gender": "female"}, {"word": "company", "gender": "female"}, {"word": "chimpanzee", "gender": "female"}, {"word": "sylph", "gender": "female"}, {"word": "outlawry", "gender": "female"}, {"word": "impulse", "gender": "female"}, {"word": "abigail", "gender": "female"}, {"word": "eden", "gender": "female"}, {"word": "policemen", "gender": "female"}, {"word": "clergy", "gender": "female"}, {"word": "deb", "gender": "female"}, {"word": "male", "gender": "female"}, {"word": "professions", "gender": "female"}, {"word": "matchmaking", "gender": "female"}, {"word": "suffragist", "gender": "female"}, {"word": "prose", "gender": "female"}, {"word": "cows", "gender": "female"}, {"word": "dress", "gender": "female"}, {"word": "offspring", "gender": "female"}, {"word": "siren", "gender": "female"}, {"word": "gringa", "gender": "female"}, {"word": "oblate", "gender": "female"}, {"word": "footman", "gender": "female"}, {"word": "coeds", "gender": "female"}, {"word": "rapists", "gender": "female"}, {"word": "charms", "gender": "female"}, {"word": "petite", "gender": "female"}, {"word": "divinities", "gender": "female"}, {"word": "directress", "gender": "female"}, {"word": "synagogue", "gender": "female"}, {"word": "softball", "gender": "female"}, {"word": "masculinization", "gender": "female"}, {"word": "merman", "gender": "female"}, {"word": "dickcissel", "gender": "female"}, {"word": "coat", "gender": "female"}, {"word": "rosebud", "gender": "female"}, {"word": "volleyball", "gender": "female"}, {"word": "caul", "gender": "female"}, {"word": "childbearing", "gender": "female"}, {"word": "sodomy", "gender": "female"}, {"word": "swordtail", "gender": "female"}, {"word": "egg", "gender": "female"}, {"word": "mestiza", "gender": "female"}, {"word": "chicks", "gender": "female"}, {"word": "infant", "gender": "female"}, {"word": "minge", "gender": "female"}, {"word": "bris", "gender": "female"}, {"word": "urine", "gender": "female"}, {"word": "brit", "gender": "female"}, {"word": "skivvies", "gender": "female"}, {"word": "eros", "gender": "female"}, {"word": "foxy", "gender": "female"}, {"word": "judges", "gender": "female"}, {"word": "millinery", "gender": "female"}, {"word": "bangle", "gender": "female"}, {"word": "abbey", "gender": "female"}, {"word": "houseparent", "gender": "female"}, {"word": "baal", "gender": "female"}, {"word": "dolly", "gender": "female"}, {"word": "eunuch", "gender": "female"}, {"word": "cutie", "gender": "female"}, {"word": "dolls", "gender": "female"}, {"word": "colleague", "gender": "female"}, {"word": "evening", "gender": "female"}, {"word": "males", "gender": "female"}, {"word": "pinafores", "gender": "female"}, {"word": "viewers", "gender": "female"}, {"word": "schoolteacher", "gender": "female"}, {"word": "pregnant", "gender": "female"}, {"word": "swimsuit", "gender": "female"}, {"word": "heroines", "gender": "female"}, {"word": "eva", "gender": "female"}, {"word": "fairy", "gender": "female"}, {"word": "brunette", "gender": "female"}, {"word": "upstairs", "gender": "female"}, {"word": "dichotomy", "gender": "female"}, {"word": "house", "gender": "female"}, {"word": "cervixes", "gender": "female"}, {"word": "beret", "gender": "female"}, {"word": "grandmothers", "gender": "female"}, {"word": "duchess", "gender": "female"}, {"word": "hermaphroditism", "gender": "female"}, {"word": "flower", "gender": "female"}, {"word": "bubby", "gender": "female"}, {"word": "blacks", "gender": "female"}, {"word": "lionesses", "gender": "female"}, {"word": "participants", "gender": "female"}, {"word": "health", "gender": "female"}, {"word": "cunnilingus", "gender": "female"}, {"word": "daddies", "gender": "female"}, {"word": "darling", "gender": "female"}, {"word": "foal", "gender": "female"}, {"word": "smock", "gender": "female"}, {"word": "chambray", "gender": "female"}, {"word": "sarong", "gender": "female"}, {"word": "pensioner", "gender": "female"}, {"word": "bombshell", "gender": "female"}, {"word": "nymphomania", "gender": "female"}, {"word": "attendant", "gender": "female"}, {"word": "pup", "gender": "female"}, {"word": "misogyny", "gender": "female"}, {"word": "housewifery", "gender": "female"}, {"word": "curtsey", "gender": "female"}, {"word": "bridegroom", "gender": "female"}, {"word": "liaison", "gender": "female"}, {"word": "contralto", "gender": "female"}, {"word": "stepmother", "gender": "female"}, {"word": "antiquity", "gender": "female"}, {"word": "slipper", "gender": "female"}, {"word": "doyenne", "gender": "female"}, {"word": "wench", "gender": "female"}, {"word": "story", "gender": "female"}, {"word": "divorce", "gender": "female"}, {"word": "hamsters", "gender": "female"}, {"word": "station", "gender": "female"}, {"word": "undies", "gender": "female"}, {"word": "mama", "gender": "female"}, {"word": "kindergartner", "gender": "female"}, {"word": "aristocracy", "gender": "female"}, {"word": "cockatiel", "gender": "female"}, {"word": "attendants", "gender": "female"}, {"word": "choirgirl", "gender": "female"}, {"word": "draper", "gender": "female"}, {"word": "blondie", "gender": "female"}, {"word": "bower", "gender": "female"}, {"word": "doctors", "gender": "female"}, {"word": "grace", "gender": "female"}, {"word": "frock", "gender": "female"}, {"word": "ogress", "gender": "female"}, {"word": "floozie", "gender": "female"}, {"word": "bride", "gender": "female"}, {"word": "marriage", "gender": "female"}, {"word": "smocking", "gender": "female"}, {"word": "phobia", "gender": "female"}, {"word": "contraception", "gender": "female"}, {"word": "gals", "gender": "female"}, {"word": "honeys", "gender": "female"}, {"word": "ages", "gender": "female"}, {"word": "affirmative", "gender": "female"}, {"word": "gale", "gender": "female"}, {"word": "blond", "gender": "female"}, {"word": "niqab", "gender": "female"}, {"word": "ballerina", "gender": "female"}, {"word": "koala", "gender": "female"}, {"word": "dancing", "gender": "female"}, {"word": "self", "gender": "female"}, {"word": "lip", "gender": "female"}, {"word": "rapist", "gender": "female"}, {"word": "monastery", "gender": "female"}, {"word": "eggs", "gender": "female"}, {"word": "flute", "gender": "female"}, {"word": "breadwinner", "gender": "female"}, {"word": "amah", "gender": "female"}, {"word": "bustier", "gender": "female"}, {"word": "daphne", "gender": "female"}, {"word": "model", "gender": "female"}, {"word": "kiddies", "gender": "female"}, {"word": "prettiness", "gender": "female"}, {"word": "areola", "gender": "female"}, {"word": "doggie", "gender": "female"}, {"word": "dystrophy", "gender": "female"}, {"word": "coven", "gender": "female"}, {"word": "chairwoman", "gender": "female"}, {"word": "maenad", "gender": "female"}, {"word": "sheik", "gender": "female"}, {"word": "housecoat", "gender": "female"}, {"word": "frocks", "gender": "female"}, {"word": "justice", "gender": "female"}, {"word": "viagra", "gender": "female"}, {"word": "condom", "gender": "female"}, {"word": "embolus", "gender": "female"}, {"word": "biddy", "gender": "female"}, {"word": "alicia", "gender": "female"}, {"word": "toddlers", "gender": "female"}, {"word": "breast", "gender": "female"}, {"word": "tunic", "gender": "female"}, {"word": "freedman", "gender": "female"}, {"word": "fianc\u00e9", "gender": "female"}, {"word": "stateswoman", "gender": "female"}, {"word": "nightshirt", "gender": "female"}, {"word": "belles", "gender": "female"}, {"word": "coffeehouse", "gender": "female"}, {"word": "knickers", "gender": "female"}, {"word": "vulva", "gender": "female"}, {"word": "leopardess", "gender": "female"}, {"word": "jade", "gender": "female"}, {"word": "activists", "gender": "female"}, {"word": "sex", "gender": "female"}, {"word": "coccyx", "gender": "female"}, {"word": "movie", "gender": "female"}, {"word": "primogeniture", "gender": "female"}, {"word": "bisexuals", "gender": "female"}, {"word": "femmes", "gender": "female"}, {"word": "rita", "gender": "female"}, {"word": "bibi", "gender": "female"}, {"word": "memsahib", "gender": "female"}, {"word": "queers", "gender": "female"}, {"word": "outfit", "gender": "female"}, {"word": "respondents", "gender": "female"}, {"word": "genders", "gender": "female"}, {"word": "succubus", "gender": "female"}, {"word": "marilyn", "gender": "female"}, {"word": "adagio", "gender": "female"}, {"word": "orphanage", "gender": "female"}, {"word": "lass", "gender": "female"}, {"word": "housecleaner", "gender": "female"}, {"word": "fiance", "gender": "female"}, {"word": "bote", "gender": "female"}, {"word": "harpy", "gender": "female"}, {"word": "wheatear", "gender": "female"}, {"word": "minorities", "gender": "female"}, {"word": "floozy", "gender": "female"}, {"word": "distress", "gender": "female"}, {"word": "chaperon", "gender": "female"}, {"word": "manners", "gender": "female"}, {"word": "gypsy", "gender": "female"}, {"word": "dances", "gender": "female"}, {"word": "dancer", "gender": "female"}, {"word": "village", "gender": "female"}, {"word": "vessel", "gender": "female"}, {"word": "pocketbook", "gender": "female"}, {"word": "wifely", "gender": "female"}, {"word": "dama", "gender": "female"}, {"word": "crinoline", "gender": "female"}, {"word": "dame", "gender": "female"}, {"word": "imam", "gender": "female"}, {"word": "alto", "gender": "female"}, {"word": "sweetheart", "gender": "female"}, {"word": "gay", "gender": "female"}, {"word": "kuya", "gender": "female"}, {"word": "wheeler", "gender": "female"}, {"word": "drainpipes", "gender": "female"}, {"word": "gal", "gender": "female"}, {"word": "lives", "gender": "female"}, {"word": "patriarchy", "gender": "female"}, {"word": "politician", "gender": "female"}, {"word": "hostess", "gender": "female"}, {"word": "governor", "gender": "female"}, {"word": "prosecutrix", "gender": "female"}, {"word": "bikini", "gender": "female"}, {"word": "sexuality", "gender": "female"}, {"word": "voters", "gender": "female"}, {"word": "urethra", "gender": "female"}, {"word": "virago", "gender": "female"}, {"word": "organs", "gender": "female"}, {"word": "bootylicious", "gender": "female"}, {"word": "ewe", "gender": "female"}, {"word": "butches", "gender": "female"}, {"word": "kimono", "gender": "female"}, {"word": "peoples", "gender": "female"}, {"word": "daughters", "gender": "female"}, {"word": "literature", "gender": "female"}, {"word": "classmates", "gender": "female"}, {"word": "husbands", "gender": "female"}, {"word": "yours", "gender": "female"}, {"word": "bourgeois", "gender": "female"}, {"word": "annunciation", "gender": "female"}, {"word": "lacrosse", "gender": "female"}, {"word": "whores", "gender": "female"}, {"word": "infertility", "gender": "female"}, {"word": "cheek", "gender": "female"}, {"word": "benefactress", "gender": "female"}, {"word": "person", "gender": "female"}, {"word": "teenybopper", "gender": "female"}, {"word": "tanager", "gender": "female"}, {"word": "pollen", "gender": "female"}, {"word": "adventuress", "gender": "female"}, {"word": "maleness", "gender": "female"}, {"word": "nylons", "gender": "female"}, {"word": "tigress", "gender": "female"}, {"word": "politesse", "gender": "female"}, {"word": "readers", "gender": "female"}, {"word": "fiancee", "gender": "female"}, {"word": "workers", "gender": "female"}, {"word": "sire", "gender": "female"}, {"word": "parents", "gender": "female"}, {"word": "cub", "gender": "female"}, {"word": "circumcision", "gender": "female"}, {"word": "mademoiselle", "gender": "female"}, {"word": "victims", "gender": "female"}, {"word": "lasses", "gender": "female"}, {"word": "chambermaid", "gender": "female"}, {"word": "couple", "gender": "female"}, {"word": "ruff", "gender": "female"}, {"word": "maidservant", "gender": "female"}, {"word": "governess", "gender": "female"}, {"word": "fagot", "gender": "female"}, {"word": "chorus", "gender": "female"}, {"word": "nipple", "gender": "female"}, {"word": "donna", "gender": "female"}, {"word": "alexandra", "gender": "female"}, {"word": "disorder", "gender": "female"}, {"word": "broadcloth", "gender": "female"}, {"word": "missus", "gender": "female"}, {"word": "fathers", "gender": "female"}, {"word": "testator", "gender": "female"}, {"word": "philandering", "gender": "female"}, {"word": "mirror", "gender": "female"}, {"word": "susie", "gender": "female"}, {"word": "pet", "gender": "female"}, {"word": "religion", "gender": "female"}, {"word": "masculinity", "gender": "female"}, {"word": "anne", "gender": "female"}, {"word": "seclusion", "gender": "female"}, {"word": "anna", "gender": "female"}, {"word": "hatpin", "gender": "female"}, {"word": "patient", "gender": "female"}, {"word": "ancestress", "gender": "female"}, {"word": "carob", "gender": "female"}, {"word": "crone", "gender": "female"}, {"word": "tefillin", "gender": "female"}, {"word": "entrepreneurs", "gender": "female"}, {"word": "homophile", "gender": "female"}, {"word": "menfolk", "gender": "female"}, {"word": "tomboy", "gender": "female"}, {"word": "clinton", "gender": "female"}, {"word": "auntie", "gender": "female"}, {"word": "maillot", "gender": "female"}, {"word": "mommy", "gender": "female"}, {"word": "comedienne", "gender": "female"}, {"word": "momma", "gender": "female"}, {"word": "katie", "gender": "female"}, {"word": "errand", "gender": "female"}, {"word": "spay", "gender": "female"}, {"word": "suit", "gender": "female"}, {"word": "bitties", "gender": "female"}, {"word": "filer", "gender": "female"}, {"word": "harem", "gender": "female"}, {"word": "narrator", "gender": "female"}, {"word": "girlfriends", "gender": "female"}, {"word": "ginkgo", "gender": "female"}, {"word": "womankind", "gender": "female"}, {"word": "zan", "gender": "female"}, {"word": "blowsy", "gender": "female"}, {"word": "cummerbund", "gender": "female"}, {"word": "gallantry", "gender": "female"}, {"word": "skull", "gender": "female"}, {"word": "culotte", "gender": "female"}, {"word": "caller", "gender": "female"}, {"word": "corsage", "gender": "female"}, {"word": "lesbianism", "gender": "female"}, {"word": "adults", "gender": "female"}, {"word": "spritely", "gender": "female"}, {"word": "stripper", "gender": "female"}, {"word": "gametes", "gender": "female"}, {"word": "ancestors", "gender": "female"}, {"word": "peach", "gender": "female"}, {"word": "nan", "gender": "female"}, {"word": "ellen", "gender": "female"}, {"word": "clitoris", "gender": "female"}, {"word": "tart", "gender": "female"}, {"word": "lena", "gender": "female"}, {"word": "gravida", "gender": "female"}, {"word": "breasts", "gender": "female"}, {"word": "frances", "gender": "female"}, {"word": "militants", "gender": "female"}, {"word": "heroine", "gender": "female"}, {"word": "policewoman", "gender": "female"}, {"word": "towpath", "gender": "female"}, {"word": "lana", "gender": "female"}, {"word": "age", "gender": "female"}, {"word": "waxing", "gender": "female"}, {"word": "chickie", "gender": "female"}, {"word": "amenorrhea", "gender": "female"}, {"word": "uterus", "gender": "female"}, {"word": "bandeau", "gender": "female"}, {"word": "corpse", "gender": "female"}, {"word": "gabardine", "gender": "female"}, {"word": "gamete", "gender": "female"}, {"word": "serviceman", "gender": "female"}, {"word": "cynthia", "gender": "female"}, {"word": "stree", "gender": "female"}, {"word": "penis", "gender": "female"}, {"word": "menses", "gender": "female"}, {"word": "kate", "gender": "female"}, {"word": "girlhood", "gender": "female"}, {"word": "saree", "gender": "female"}, {"word": "saleswoman", "gender": "female"}, {"word": "aria", "gender": "female"}, {"word": "giantess", "gender": "female"}, {"word": "masculine", "gender": "female"}, {"word": "women", "gender": "female"}, {"word": "wendy", "gender": "female"}, {"word": "squeaker", "gender": "female"}, {"word": "maam", "gender": "female"}, {"word": "seizer", "gender": "female"}, {"word": "sexist", "gender": "female"}, {"word": "abduction", "gender": "female"}, {"word": "harlot", "gender": "female"}, {"word": "carman", "gender": "female"}, {"word": "stunner", "gender": "female"}, {"word": "doggy", "gender": "female"}, {"word": "paternity", "gender": "female"}, {"word": "gender", "gender": "female"}, {"word": "race", "gender": "female"}, {"word": "barbara", "gender": "female"}, {"word": "senorita", "gender": "female"}, {"word": "queer", "gender": "female"}, {"word": "playmate", "gender": "female"}, {"word": "pajamas", "gender": "female"}, {"word": "ladyship", "gender": "female"}, {"word": "staffers", "gender": "female"}, {"word": "dowdy", "gender": "female"}, {"word": "vampire", "gender": "female"}, {"word": "valet", "gender": "female"}, {"word": "twins", "gender": "female"}, {"word": "anther", "gender": "female"}, {"word": "attire", "gender": "female"}, {"word": "kayaker", "gender": "female"}, {"word": "body", "gender": "female"}, {"word": "fertilization", "gender": "female"}, {"word": "bulimia", "gender": "female"}, {"word": "kidnapper", "gender": "female"}, {"word": "brooch", "gender": "female"}, {"word": "baroness", "gender": "female"}, {"word": "pipefish", "gender": "female"}, {"word": "matriarchy", "gender": "female"}, {"word": "brunet", "gender": "female"}, {"word": "fibroadenoma", "gender": "female"}, {"word": "cyclist", "gender": "female"}, {"word": "rosary", "gender": "female"}, {"word": "fathering", "gender": "female"}, {"word": "grandchild", "gender": "female"}, {"word": "armpit", "gender": "female"}, {"word": "chiton", "gender": "female"}, {"word": "pajama", "gender": "female"}, {"word": "sheila", "gender": "female"}, {"word": "crumpet", "gender": "female"}, {"word": "shalwar", "gender": "female"}, {"word": "pillion", "gender": "female"}, {"word": "cheerleader", "gender": "female"}, {"word": "singing", "gender": "female"}, {"word": "chieftainess", "gender": "female"}, {"word": "fem", "gender": "female"}, {"word": "ministers", "gender": "female"}, {"word": "sodomite", "gender": "female"}, {"word": "strapper", "gender": "female"}, {"word": "phallus", "gender": "female"}, {"word": "cheeks", "gender": "female"}, {"word": "clergywomen", "gender": "female"}, {"word": "babe", "gender": "female"}, {"word": "babu", "gender": "female"}, {"word": "baby", "gender": "female"}, {"word": "casserole", "gender": "female"}, {"word": "charity", "gender": "female"}, {"word": "concierge", "gender": "female"}, {"word": "animals", "gender": "female"}, {"word": "duster", "gender": "female"}, {"word": "clients", "gender": "female"}, {"word": "pouf", "gender": "female"}, {"word": "dressmaker", "gender": "female"}, {"word": "confidante", "gender": "female"}, {"word": "patron", "gender": "female"}, {"word": "etta", "gender": "female"}, {"word": "tootsie", "gender": "female"}, {"word": "slit", "gender": "female"}, {"word": "pelvis", "gender": "female"}, {"word": "skirt", "gender": "female"}, {"word": "rape", "gender": "female"}, {"word": "sis", "gender": "female"}, {"word": "aviatrix", "gender": "female"}, {"word": "procurer", "gender": "female"}, {"word": "syndrome", "gender": "female"}, {"word": "lamp", "gender": "female"}, {"word": "animal", "gender": "female"}, {"word": "hormones", "gender": "female"}, {"word": "toddler", "gender": "female"}, {"word": "gurl", "gender": "female"}, {"word": "administrator", "gender": "female"}, {"word": "maternal", "gender": "female"}, {"word": "frak", "gender": "female"}, {"word": "leukemia", "gender": "female"}, {"word": "frau", "gender": "female"}, {"word": "abuse", "gender": "female"}, {"word": "cabbage", "gender": "female"}, {"word": "lecher", "gender": "female"}, {"word": "solon", "gender": "female"}, {"word": "bakery", "gender": "female"}, {"word": "laurie", "gender": "female"}, {"word": "nancy", "gender": "female"}, {"word": "ovipositor", "gender": "female"}, {"word": "bint", "gender": "female"}, {"word": "volunteers", "gender": "female"}, {"word": "jolie", "gender": "female"}, {"word": "gondolier", "gender": "female"}, {"word": "kindergarteners", "gender": "female"}, {"word": "flapper", "gender": "female"}, {"word": "banyan", "gender": "female"}, {"word": "magnesia", "gender": "female"}, {"word": "gynecology", "gender": "female"}, {"word": "damsel", "gender": "female"}, {"word": "whitey", "gender": "female"}, {"word": "sperm", "gender": "female"}, {"word": "swain", "gender": "female"}, {"word": "palanquin", "gender": "female"}, {"word": "costume", "gender": "female"}, {"word": "obstetrics", "gender": "female"}, {"word": "bunco", "gender": "female"}, {"word": "interpreter", "gender": "female"}, {"word": "horny", "gender": "female"}, {"word": "bosomed", "gender": "female"}, {"word": "housewife", "gender": "female"}, {"word": "labor", "gender": "female"}, {"word": "degrees", "gender": "female"}, {"word": "chimney", "gender": "female"}, {"word": "turban", "gender": "female"}, {"word": "redhead", "gender": "female"}, {"word": "prophetess", "gender": "female"}, {"word": "paramour", "gender": "female"}, {"word": "dam", "gender": "female"}, {"word": "elephant", "gender": "female"}, {"word": "kiss", "gender": "female"}, {"word": "flea", "gender": "female"}, {"word": "affections", "gender": "female"}, {"word": "housemaster", "gender": "female"}, {"word": "applicants", "gender": "female"}, {"word": "university", "gender": "female"}, {"word": "lingerie", "gender": "female"}, {"word": "betty", "gender": "female"}, {"word": "princesses", "gender": "female"}, {"word": "widower", "gender": "female"}, {"word": "nationals", "gender": "female"}, {"word": "testatrix", "gender": "female"}, {"word": "cry", "gender": "female"}, {"word": "anklet", "gender": "female"}, {"word": "skank", "gender": "female"}, {"word": "society", "gender": "female"}, {"word": "collegian", "gender": "female"}, {"word": "coatroom", "gender": "female"}, {"word": "semen", "gender": "female"}, {"word": "mandrill", "gender": "female"}, {"word": "boutique", "gender": "female"}, {"word": "feminisation", "gender": "female"}, {"word": "burka", "gender": "female"}, {"word": "jessica", "gender": "female"}, {"word": "jilt", "gender": "female"}, {"word": "abductor", "gender": "female"}, {"word": "jill", "gender": "female"}, {"word": "levitra", "gender": "female"}, {"word": "administratrix", "gender": "female"}, {"word": "princess", "gender": "female"}, {"word": "shrew", "gender": "female"}, {"word": "river", "gender": "female"}, {"word": "alderwoman", "gender": "female"}, {"word": "widowhood", "gender": "female"}, {"word": "enfranchisement", "gender": "female"}, {"word": "pigs", "gender": "female"}, {"word": "protagonists", "gender": "female"}, {"word": "waitress", "gender": "female"}, {"word": "yoni", "gender": "female"}, {"word": "bonnet", "gender": "female"}, {"word": "bitch", "gender": "female"}, {"word": "filial", "gender": "female"}, {"word": "scent", "gender": "female"}, {"word": "lolita", "gender": "female"}, {"word": "vixen", "gender": "female"}, {"word": "thirties", "gender": "female"}, {"word": "accent", "gender": "female"}, {"word": "wrapper", "gender": "female"}, {"word": "scullers", "gender": "female"}, {"word": "vagina", "gender": "female"}, {"word": "maidens", "gender": "female"}, {"word": "polygyny", "gender": "female"}, {"word": "baronet", "gender": "female"}, {"word": "cabin", "gender": "female"}, {"word": "alopecia", "gender": "female"}, {"word": "megan", "gender": "female"}, {"word": "rickshaw", "gender": "female"}, {"word": "manhole", "gender": "female"}, {"word": "mules", "gender": "female"}, {"word": "herself", "gender": "female"}, {"word": "newlywed", "gender": "female"}, {"word": "plumage", "gender": "female"}, {"word": "photograph", "gender": "female"}, {"word": "patriarchic", "gender": "female"}, {"word": "girdle", "gender": "female"}, {"word": "breadwinners", "gender": "female"}, {"word": "bed", "gender": "female"}, {"word": "patients", "gender": "female"}, {"word": "lover", "gender": "female"}, {"word": "whoremonger", "gender": "female"}, {"word": "sculpture", "gender": "female"}, {"word": "bodice", "gender": "female"}, {"word": "beggar", "gender": "female"}, {"word": "viewer", "gender": "female"}, {"word": "bisexual", "gender": "female"}, {"word": "teenagers", "gender": "female"}, {"word": "faun", "gender": "female"}, {"word": "border", "gender": "female"}, {"word": "pupils", "gender": "female"}, {"word": "millionairess", "gender": "female"}, {"word": "patroness", "gender": "female"}, {"word": "relatives", "gender": "female"}, {"word": "latina", "gender": "female"}, {"word": "babes", "gender": "female"}, {"word": "zenana", "gender": "female"}, {"word": "lily", "gender": "female"}, {"word": "girlies", "gender": "female"}, {"word": "spinster", "gender": "female"}, {"word": "redstart", "gender": "female"}, {"word": "caftan", "gender": "female"}, {"word": "pakeha", "gender": "female"}, {"word": "necklace", "gender": "female"}, {"word": "handbag", "gender": "female"}, {"word": "peignoir", "gender": "female"}, {"word": "polyandry", "gender": "female"}, {"word": "soubrette", "gender": "female"}, {"word": "looker", "gender": "female"}, {"word": "peplum", "gender": "female"}, {"word": "bree", "gender": "female"}, {"word": "pipe", "gender": "female"}, {"word": "capita", "gender": "female"}, {"word": "pictures", "gender": "female"}, {"word": "painting", "gender": "female"}, {"word": "affair", "gender": "female"}, {"word": "gail", "gender": "female"}, {"word": "hamlet", "gender": "female"}, {"word": "bedroom", "gender": "female"}, {"word": "jailbait", "gender": "female"}, {"word": "soldiers", "gender": "female"}, {"word": "chicken", "gender": "female"}, {"word": "handmaid", "gender": "female"}, {"word": "sheriff", "gender": "female"}, {"word": "proprietress", "gender": "female"}, {"word": "caravel", "gender": "female"}, {"word": "ethan", "gender": "female"}, {"word": "employee", "gender": "female"}, {"word": "girlie", "gender": "female"}, {"word": "thousands", "gender": "female"}, {"word": "cloche", "gender": "female"}, {"word": "sweetie", "gender": "female"}, {"word": "beau", "gender": "female"}, {"word": "flirting", "gender": "female"}, {"word": "cubs", "gender": "female"}, {"word": "homosexuals", "gender": "female"}, {"word": "organ", "gender": "female"}, {"word": "virginal", "gender": "female"}, {"word": "plumpness", "gender": "female"}, {"word": "she", "gender": "female"}, {"word": "nightingale", "gender": "female"}, {"word": "mumsy", "gender": "female"}, {"word": "marries", "gender": "female"}, {"word": "generations", "gender": "female"}, {"word": "widow", "gender": "female"}, {"word": "madam", "gender": "female"}, {"word": "pronoun", "gender": "female"}, {"word": "preadolescence", "gender": "female"}, {"word": "humans", "gender": "female"}, {"word": "canine", "gender": "female"}, {"word": "blackbuck", "gender": "female"}, {"word": "violet", "gender": "female"}, {"word": "racket", "gender": "female"}, {"word": "pageboy", "gender": "female"}, {"word": "unionists", "gender": "female"}, {"word": "literate", "gender": "female"}, {"word": "thong", "gender": "female"}, {"word": "state", "gender": "female"}, {"word": "panty", "gender": "female"}, {"word": "dominatrix", "gender": "female"}, {"word": "adriana", "gender": "female"}, {"word": "andromeda", "gender": "female"}, {"word": "housemother", "gender": "female"}, {"word": "heiress", "gender": "female"}, {"word": "abusers", "gender": "female"}, {"word": "effeminacy", "gender": "female"}, {"word": "erin", "gender": "female"}, {"word": "piece", "gender": "female"}, {"word": "barrette", "gender": "female"}, {"word": "heterosexuality", "gender": "female"}, {"word": "carhop", "gender": "female"}, {"word": "sexes", "gender": "female"}, {"word": "heart", "gender": "female"}, {"word": "phylactery", "gender": "female"}, {"word": "undergraduates", "gender": "female"}, {"word": "denise", "gender": "female"}, {"word": "hussy", "gender": "female"}, {"word": "sari", "gender": "female"}, {"word": "seraglio", "gender": "female"}, {"word": "discrimination", "gender": "female"}, {"word": "libber", "gender": "female"}, {"word": "bbw", "gender": "female"}, {"word": "troopers", "gender": "female"}, {"word": "cocotte", "gender": "female"}, {"word": "coverture", "gender": "female"}, {"word": "gymnasts", "gender": "female"}, {"word": "puberty", "gender": "female"}, {"word": "schoolgirls", "gender": "female"}, {"word": "dalaga", "gender": "female"}, {"word": "mannequin", "gender": "female"}, {"word": "kerchief", "gender": "female"}, {"word": "corset", "gender": "female"}, {"word": "sterility", "gender": "female"}, {"word": "meridian", "gender": "female"}, {"word": "misandrist", "gender": "female"}, {"word": "foundress", "gender": "female"}, {"word": "adulterer", "gender": "female"}, {"word": "bolero", "gender": "female"}, {"word": "pantie", "gender": "female"}, {"word": "resident", "gender": "female"}, {"word": "evelyn", "gender": "female"}, {"word": "lust", "gender": "female"}, {"word": "universalism", "gender": "female"}, {"word": "conductress", "gender": "female"}, {"word": "transvestite", "gender": "female"}, {"word": "partner", "gender": "female"}, {"word": "bondswoman", "gender": "female"}, {"word": "deed", "gender": "female"}, {"word": "whore", "gender": "female"}, {"word": "doula", "gender": "female"}, {"word": "romance", "gender": "female"}, {"word": "speaker", "gender": "female"}, {"word": "misogynist", "gender": "female"}, {"word": "inamorata", "gender": "female"}, {"word": "android", "gender": "female"}, {"word": "eugenic", "gender": "female"}, {"word": "stamen", "gender": "female"}, {"word": "fur", "gender": "female"}, {"word": "slave", "gender": "female"}, {"word": "preteen", "gender": "female"}, {"word": "fecundity", "gender": "female"}, {"word": "student", "gender": "female"}, {"word": "sisters", "gender": "female"}, {"word": "sibs", "gender": "female"}, {"word": "kirpan", "gender": "female"}, {"word": "vinaigrette", "gender": "female"}, {"word": "carrie", "gender": "female"}, {"word": "flesh", "gender": "female"}, {"word": "wren", "gender": "female"}, {"word": "cries", "gender": "female"}, {"word": "barmaid", "gender": "female"}, {"word": "tch", "gender": "female"}, {"word": "laurel", "gender": "female"}, {"word": "courtship", "gender": "female"}, {"word": "femme", "gender": "female"}, {"word": "ovum", "gender": "female"}, {"word": "lanugo", "gender": "female"}, {"word": "clothier", "gender": "female"}, {"word": "citizen", "gender": "female"}, {"word": "myth", "gender": "female"}, {"word": "chancellor", "gender": "female"}, {"word": "livia", "gender": "female"}, {"word": "slattern", "gender": "female"}, {"word": "wooer", "gender": "female"}, {"word": "desk", "gender": "female"}, {"word": "culottes", "gender": "female"}, {"word": "puppy", "gender": "female"}, {"word": "emma", "gender": "female"}, {"word": "housekeeper", "gender": "female"}, {"word": "manageress", "gender": "female"}, {"word": "chica", "gender": "female"}, {"word": "ponytail", "gender": "female"}, {"word": "divorcees", "gender": "female"}, {"word": "chick", "gender": "female"}, {"word": "refugees", "gender": "female"}, {"word": "virginity", "gender": "female"}, {"word": "church", "gender": "female"}, {"word": "hair", "gender": "female"}, {"word": "darlin", "gender": "female"}, {"word": "gymnastics", "gender": "female"}, {"word": "shes", "gender": "female"}, {"word": "headship", "gender": "female"}, {"word": "trainman", "gender": "female"}, {"word": "pompon", "gender": "female"}, {"word": "jurisprudence", "gender": "female"}, {"word": "leah", "gender": "female"}, {"word": "fountain", "gender": "female"}, {"word": "castrato", "gender": "female"}, {"word": "copulation", "gender": "female"}, {"word": "therapists", "gender": "female"}, {"word": "kiddo", "gender": "female"}, {"word": "castrate", "gender": "female"}, {"word": "poets", "gender": "female"}, {"word": "sherwani", "gender": "female"}, {"word": "slut", "gender": "female"}, {"word": "iris", "gender": "female"}, {"word": "sister", "gender": "female"}, {"word": "testosterone", "gender": "female"}, {"word": "embryos", "gender": "female"}, {"word": "usherette", "gender": "female"}, {"word": "madame", "gender": "female"}, {"word": "union", "gender": "female"}, {"word": "carrier", "gender": "female"}, {"word": "udder", "gender": "female"}, {"word": "artiste", "gender": "female"}, {"word": "cadet", "gender": "female"}, {"word": "clotheshorse", "gender": "female"}, {"word": "debutante", "gender": "female"}, {"word": "travelers", "gender": "female"}, {"word": "catherine", "gender": "female"}, {"word": "female", "gender": "female"}, {"word": "artists", "gender": "female"}, {"word": "swimmers", "gender": "female"}, {"word": "milkmaid", "gender": "female"}, {"word": "parentage", "gender": "female"}, {"word": "brownies", "gender": "female"}, {"word": "adolescent", "gender": "female"}, {"word": "brides", "gender": "female"}, {"word": "cinderella", "gender": "female"}, {"word": "manteau", "gender": "female"}, {"word": "catamaran", "gender": "female"}, {"word": "ejaculation", "gender": "female"}, {"word": "bus", "gender": "female"}, {"word": "fascinator", "gender": "female"}, {"word": "washerwoman", "gender": "female"}, {"word": "bun", "gender": "female"}, {"word": "granny", "gender": "female"}, {"word": "bub", "gender": "female"}, {"word": "stepsister", "gender": "female"}, {"word": "genitals", "gender": "female"}, {"word": "dozens", "gender": "female"}, {"word": "congresswoman", "gender": "female"}, {"word": "infanticide", "gender": "female"}, {"word": "nightgown", "gender": "female"}, {"word": "broads", "gender": "female"}, {"word": "carriage", "gender": "female"}, {"word": "showgirl", "gender": "female"}, {"word": "infants", "gender": "female"}, {"word": "gynecological", "gender": "female"}, {"word": "menstruation", "gender": "female"}, {"word": "rabbits", "gender": "female"}, {"word": "jenny", "gender": "female"}, {"word": "deaths", "gender": "female"}, {"word": "nurses", "gender": "female"}, {"word": "sexpot", "gender": "female"}, {"word": "horsewoman", "gender": "female"}, {"word": "pig", "gender": "female"}, {"word": "nymphet", "gender": "female"}, {"word": "buffa", "gender": "female"}, {"word": "attributive", "gender": "female"}, {"word": "preschooler", "gender": "female"}, {"word": "speculum", "gender": "female"}, {"word": "wimple", "gender": "female"}, {"word": "anopheles", "gender": "female"}, {"word": "chemise", "gender": "female"}, {"word": "midwifery", "gender": "female"}, {"word": "headmistress", "gender": "female"}, {"word": "shepherdess", "gender": "female"}, {"word": "boob", "gender": "female"}, {"word": "parthenogenesis", "gender": "female"}, {"word": "dresses", "gender": "female"}, {"word": "juno", "gender": "female"}, {"word": "butch", "gender": "female"}, {"word": "oppression", "gender": "female"}, {"word": "veil", "gender": "female"}, {"word": "ovary", "gender": "female"}, {"word": "sistah", "gender": "female"}, {"word": "quetzal", "gender": "female"}, {"word": "adulteress", "gender": "female"}, {"word": "coquette", "gender": "female"}, {"word": "hiker", "gender": "female"}, {"word": "elaine", "gender": "female"}, {"word": "pupil", "gender": "female"}, {"word": "heidi", "gender": "female"}, {"word": "katherine", "gender": "female"}, {"word": "sash", "gender": "female"}]